{
  "db_name": "PostgreSQL",
  "query": "\n            INSERT INTO categories (\n                id, parent_id, name, slug, type, description,\n                created_at, updated_at, deleted_at\n            )\n            VALUES ($1, $2, $3, $4, $5, $6, NOW(), NOW(), NULL)\n            RETURNING id, parent_id, name, slug, type, description,\n                      created_at, updated_at, deleted_at\n            ",
  "describe": {
    "columns": [
      {
        "ordinal": 0,
        "name": "id",
        "type_info": "Uuid"
      },
      {
        "ordinal": 1,
        "name": "parent_id",
        "type_info": "Uuid"
      },
      {
        "ordinal": 2,
        "name": "name",
        "type_info": "Text"
      },
      {
        "ordinal": 3,
        "name": "slug",
        "type_info": "Text"
      },
      {
        "ordinal": 4,
        "name": "type",
        "type_info": "Text"
      },
      {
        "ordinal": 5,
        "name": "description",
        "type_info": "Text"
      },
      {
        "ordinal": 6,
        "name": "created_at",
        "type_info": "Timestamp"
      },
      {
        "ordinal": 7,
        "name": "updated_at",
        "type_info": "Timestamp"
      },
      {
        "ordinal": 8,
        "name": "deleted_at",
        "type_info": "Timestamp"
      }
    ],
    "parameters": {
      "Left": [
        "Uuid",
        "Uuid",
        "Text",
        "Text",
        "Text",
        "Text"
      ]
    },
    "nullable": [
      false,
      true,
      false,
      true,
      false,
      true,
      true,
      true,
      true
    ]
  },
  "hash": "18f9744bcbadf1a125de53da4c3cb4b890e31a741755f8d1a76d510bbb7c46f0"
}
